aiscalator/__init__.py
aiscalator/api.py
aiscalator/cli.py
aiscalator/airflow/__init__.py
aiscalator/airflow/cli.py
aiscalator/airflow/command.py
aiscalator/config/docker/airflow/Dockerfile
aiscalator/config/docker/airflow/jupyter_notebook_config.txt
aiscalator/config/docker/airflow/req_docker.txt
aiscalator/config/docker/airflow/start-jupyter.sh
aiscalator/config/docker/airflow/config/airflow.cfg
aiscalator/config/docker/airflow/config/docker-compose-CeleryExecutor.yml
aiscalator/config/docker/airflow/config/docker-compose-LocalExecutor.yml
aiscalator/config/docker/jupyter-dbt/Dockerfile
aiscalator/config/docker/jupyter-dbt/install-jupytext.sh
aiscalator/config/docker/jupyter-dbt/req_docker.txt
aiscalator/config/docker/jupyter-dbt/start-papermill.sh
aiscalator/config/docker/jupyter-spark/Dockerfile
aiscalator/config/docker/jupyter-spark/install-jupytext.sh
aiscalator/config/docker/jupyter-spark/req_docker.txt
aiscalator/config/docker/jupyter-spark/start-papermill.sh
aiscalator/config/template/aiscalator.conf
aiscalator/config/template/minimum_aiscalator.conf
aiscalator/config/template/minimum_dag.conf
aiscalator/config/template/minimum_step.conf
aiscalator/config/template/notebook.json
aiscalator/config/template/step.conf
aiscalator/core/__init__.py
aiscalator/core/config.py
aiscalator/core/log_regex_analyzer.py
aiscalator/core/utils.py
aiscalator/jupyter/__init__.py
aiscalator/jupyter/cli.py
aiscalator/jupyter/command.py
aiscalator/jupyter/docker_image.py
aiscalator-0.1.18.dist-info/AUTHORS.rst
aiscalator-0.1.18.dist-info/LICENSE
aiscalator-0.1.18.dist-info/METADATA
aiscalator-0.1.18.dist-info/WHEEL
aiscalator-0.1.18.dist-info/entry_points.txt
aiscalator-0.1.18.dist-info/top_level.txt
aiscalator-0.1.18.dist-info/RECORD
