Metadata-Version: 2.1
Name: aiscalator
Version: 0.1.18
Summary: AIscalate your Jupyter Notebook Prototypes into Airflow Data Products
Home-page: https://github.com/Aiscalate/aiscalator
Author: Christophe Duong
Author-email: chris@aiscalate.com
License: Apache Software License 2.0
Keywords: data science,jupyter,jupyter notebook,prototype,papermill,jupytext,data engineering,product,airflow
Platform: UNKNOWN
Classifier: Development Status :: 3 - Alpha
Classifier: Intended Audience :: Developers
Classifier: Intended Audience :: Science/Research
Classifier: Intended Audience :: System Administrators
Classifier: License :: OSI Approved :: Apache Software License
Classifier: Natural Language :: English
Classifier: Operating System :: Unix
Classifier: Operating System :: POSIX
Classifier: Programming Language :: Python
Classifier: Programming Language :: Python :: 3
Classifier: Programming Language :: Python :: 3.4
Classifier: Programming Language :: Python :: 3.5
Classifier: Programming Language :: Python :: 3.6
Classifier: Programming Language :: Python :: 3.7
Classifier: Programming Language :: Python :: Implementation :: PyPy
Classifier: Topic :: Utilities
Classifier: Topic :: Scientific/Engineering :: Artificial Intelligence
Classifier: Topic :: Software Development :: Libraries :: Application Frameworks
Requires-Dist: Click (>=6.0)
Requires-Dist: jupytext (>=1.5.2)
Requires-Dist: pyhocon (>=0.3.48)
Requires-Dist: pytz (>=2018.5)
